colcon_coveragepy_result/__init__.py
colcon_coveragepy_result/task/__init__.py
colcon_coveragepy_result/task/coveragepy.py
colcon_coveragepy_result/verb/__init__.py
colcon_coveragepy_result/verb/coveragepy_result.py
colcon_coveragepy_result-0.0.8.dist-info/LICENSE
colcon_coveragepy_result-0.0.8.dist-info/METADATA
colcon_coveragepy_result-0.0.8.dist-info/WHEEL
colcon_coveragepy_result-0.0.8.dist-info/entry_points.txt
colcon_coveragepy_result-0.0.8.dist-info/top_level.txt
colcon_coveragepy_result-0.0.8.dist-info/RECORD
