Metadata-Version: 2.1
Name: colcon-coveragepy-result
Version: 0.0.8
Summary: colcon extension for collecting coverage.py results
Home-page: https://colcon.readthedocs.io
Author: Christophe Bedard
Author-email: bedard.christophe@gmail.com
Maintainer: Christophe Bedard
Maintainer-email: bedard.christophe@gmail.com
License: Apache License, Version 2.0
Project-URL: Changelog, https://github.com/colcon/colcon-coveragepy-result/milestones?state=closed
Project-URL: GitHub, https://github.com/colcon/colcon-coveragepy-result/
Keywords: colcon,coverage
Platform: UNKNOWN
Classifier: Development Status :: 3 - Alpha
Classifier: Environment :: Console
Classifier: Environment :: Plugins
Classifier: Intended Audience :: Developers
Classifier: License :: OSI Approved :: Apache Software License
Classifier: Operating System :: MacOS
Classifier: Operating System :: Microsoft :: Windows
Classifier: Operating System :: POSIX
Classifier: Programming Language :: Python
Classifier: Topic :: Software Development :: Build Tools
Requires-Python: >=3.5
Requires-Dist: colcon-core
Requires-Dist: coverage
